bagheera/__init__.py
bagheera/cli.py
bagheera/main.py
bagheera/parser/__init__.py
bagheera/parser/errors.py
bagheera/parser/parser.py
bagheera-0.0.13.dist-info/LICENSE
bagheera-0.0.13.dist-info/METADATA
bagheera-0.0.13.dist-info/WHEEL
bagheera-0.0.13.dist-info/entry_points.txt
bagheera-0.0.13.dist-info/top_level.txt
bagheera-0.0.13.dist-info/RECORD
