Metadata-Version: 2.1
Name: bagheera
Version: 0.0.13
Summary: An implementation of the bagheera programming language
Home-page: https://github.com/bagheera-lang/bagheera-python
Author: Bagheera
Author-email: bergmann.jerome@gmail.com
License: UNKNOWN
Platform: UNKNOWN
Classifier: Programming Language :: Python :: 3
Classifier: License :: OSI Approved :: MIT License
Classifier: Operating System :: OS Independent
Requires-Python: >=3.4
Requires-Dist: pyparsing
